toolkitx/__init__.py
toolkitx/hello.py
toolkitx/text_utils.py
toolkitx/lab/__init__.py
toolkitx/lab/translator.py
toolkitx-0.0.3.dist-info/METADATA
toolkitx-0.0.3.dist-info/WHEEL
toolkitx-0.0.3.dist-info/entry_points.txt
toolkitx-0.0.3.dist-info/licenses/LICENSE
toolkitx-0.0.3.dist-info/RECORD
