Metadata-Version: 2.4
Name: toolkitx
Version: 0.0.3
Summary: A personal Python toolkit for common tasks
Project-URL: Homepage, https://github.com/ider-zh/toolkitx
Project-URL: Bug Tracker, https://github.com/ider-zh/toolkitx/issues
License-File: LICENSE
Requires-Python: >=3.12
Requires-Dist: diskcache>=5.6.3
Requires-Dist: httpx>=0.27.2
Requires-Dist: tencentcloud-sdk-python>=3.0.681
Provides-Extra: dev
Requires-Dist: pytest; extra == 'dev'
Requires-Dist: pytest-dotenv; extra == 'dev'
